{"type":"Topology","transform":{"scale":[581.5466922692268,503.2369740974098],"translate":[-11100449.2798,2532912.4481]},"objects":{"twenty-seven-admin0-lines":{"type":"GeometryCollection","geometries":[{"type":"LineString","arcs":[0]},{"type":"LineString","arcs":[1]},{"type":"LineString","arcs":[2]},{"type":"LineString","arcs":[3]},{"type":"LineString","arcs":[4]}]}},"arcs":[[[9999,3978],[-140,444],[-206,86],[-160,-509],[-56,0],[-23,-71],[-256,0],[-137,0],[-79,0],[-127,-147]],[[7899,3526],[-61,-194]],[[3286,1123],[306,129],[3,1],[608,-256],[125,0],[122,0],[0,150],[223,0],[480,-554],[147,170],[411,-658],[249,-105]],[[6857,4561],[-531,223],[-85,98],[-39,-45],[-328,0],[-563,0],[-307,0],[-807,0],[-472,0],[-340,0],[-124,0],[-803,0]],[[1427,6247],[0,274],[-735,848],[-195,-130],[-288,333],[0,-1],[-209,0],[0,2428]]]}